<Namespace Name="System.Configuration.Internal">
  <Metadata>
    <Meta Name="ms.openlocfilehash" Value="8c38a213a8993da5f4b6f306821196b0197b82c3" />
    <Meta Name="ms.sourcegitcommit" Value="df6cf590aa3087f6c7c202712eee781c6a3c8f96" />
    <Meta Name="ms.translationtype" Value="HT" />
    <Meta Name="ms.contentlocale" Value="zh-CN" />
    <Meta Name="ms.lasthandoff" Value="05/10/2018" />
    <Meta Name="ms.locfileid" Value="30726171" />
  </Metadata>
  <Docs>
    <summary>
      <see cref="N:System.Configuration.Internal" /> 命名空间包含仅供内部使用的配置类型。</summary>
    <remarks>To be added.</remarks>
  </Docs>
</Namespace>