<?xml version="1.0" encoding="utf-8"?>
<xliff xmlns="urn:oasis:names:tc:xliff:document:1.2" xmlns:xsi="http://www.w3.org/2001/XMLSchema-instance" version="1.2" xsi:schemaLocation="urn:oasis:names:tc:xliff:document:1.2 xliff-core-1.2-transitional.xsd">
  <file datatype="xml" original="IContractBehaviorAttribute.xml" source-language="en-US" target-language="zh-CN">
    <header>
      <tool tool-id="mdxliff" tool-name="mdxliff" tool-version="1.0-15c36f0" tool-company="Microsoft" />
      <xliffext:skl_file_name xmlns:xliffext="urn:microsoft:content:schema:xliffextensions">02cd5861-7ce2-4a82-b358-31f8435a0ac5c49274278dbaf51e1412020923ae5709dcab6cca.skl</xliffext:skl_file_name>
      <xliffext:version xmlns:xliffext="urn:microsoft:content:schema:xliffextensions">1.2</xliffext:version>
      <xliffext:ms.openlocfilehash xmlns:xliffext="urn:microsoft:content:schema:xliffextensions">c49274278dbaf51e1412020923ae5709dcab6cca</xliffext:ms.openlocfilehash>
      <xliffext:ms.sourcegitcommit xmlns:xliffext="urn:microsoft:content:schema:xliffextensions">d31dc2ede16f6f7bc64e90d9f897ff54c4e3869b</xliffext:ms.sourcegitcommit>
      <xliffext:ms.lasthandoff xmlns:xliffext="urn:microsoft:content:schema:xliffextensions">04/03/2018</xliffext:ms.lasthandoff>
      <xliffext:moniker_ids xmlns:xliffext="urn:microsoft:content:schema:xliffextensions">netframework-4.5.1,netframework-4.5.2,netframework-4.5,netframework-4.6.1,netframework-4.6.2,netframework-4.6,netframework-4.7.1,netframework-4.7</xliffext:moniker_ids>
    </header>
    <body>
      <group id="content" extype="content">
        <trans-unit id="101" translate="yes" xml:space="preserve" uid="T:System.ServiceModel.Description.IContractBehaviorAttribute">
          <source>Specifies the contract for which an attribute that implements the <ph id="ph1">&lt;see cref="T:System.ServiceModel.Description.IContractBehavior" /&gt;</ph> interface is active.</source>
          <target state="translated">指定其实现 <ph id="ph1">&lt;see cref="T:System.ServiceModel.Description.IContractBehavior" /&gt;</ph> 接口的属性处于活动状态的协定。</target>       </trans-unit>
        <trans-unit id="102" translate="yes" xml:space="preserve" extradata="MT" uid="T:System.ServiceModel.Description.IContractBehaviorAttribute">
          <source>Implement the <ph id="ph1">&lt;xref:System.ServiceModel.Description.IContractBehaviorAttribute&gt;</ph> interface on an attribute that is also an <ph id="ph2">&lt;xref:System.ServiceModel.Description.IContractBehavior?displayProperty=nameWithType&gt;</ph> object to enable the use of that contract behavior attribute on a service type but restrict its application to the contract specified in the <ph id="ph3">&lt;xref:System.ServiceModel.Description.IContractBehaviorAttribute.TargetContract%2A&gt;</ph> property.</source>
          <target state="translated">对一个同时为 <ph id="ph1">&lt;xref:System.ServiceModel.Description.IContractBehaviorAttribute&gt;</ph> 对象的属性实现 <ph id="ph2">&lt;xref:System.ServiceModel.Description.IContractBehavior?displayProperty=nameWithType&gt;</ph> 接口可以对服务类型使用该协定行为属性，但会将此属性的使用限定为 <ph id="ph3">&lt;xref:System.ServiceModel.Description.IContractBehaviorAttribute.TargetContract%2A&gt;</ph> 属性中指定的协定。</target>       </trans-unit>
        <trans-unit id="103" translate="yes" xml:space="preserve" extradata="MT" uid="T:System.ServiceModel.Description.IContractBehaviorAttribute">
          <source>There is no requirement to implement <ph id="ph1">&lt;xref:System.ServiceModel.Description.IContractBehaviorAttribute&gt;</ph> on custom contract behavior attributes, and if the attribute is applied either to a contract interface or to a duplex callback class the value of the <ph id="ph2">&lt;xref:System.ServiceModel.Description.IContractBehaviorAttribute.TargetContract%2A&gt;</ph> property is ignored.</source>
          <target state="translated">不要求在自定义协定行为属性上实现 <ph id="ph1">&lt;xref:System.ServiceModel.Description.IContractBehaviorAttribute&gt;</ph>，如果该属性应用到协定接口或双向回调类，则将忽略 <ph id="ph2">&lt;xref:System.ServiceModel.Description.IContractBehaviorAttribute.TargetContract%2A&gt;</ph> 属性的值。</target>       </trans-unit>
        <trans-unit id="104" translate="yes" xml:space="preserve" extradata="MT" uid="T:System.ServiceModel.Description.IContractBehaviorAttribute">
          <source>For more information, see <ph id="ph1">&lt;xref:System.ServiceModel.Description.IContractBehavior?displayProperty=nameWithType&gt;</ph>.</source>
          <target state="translated">有关详情，请参阅<ph id="ph1">&lt;xref:System.ServiceModel.Description.IContractBehavior?displayProperty=nameWithType&gt;</ph>。</target>       </trans-unit>
        <trans-unit id="105" translate="yes" xml:space="preserve" extradata="MT" uid="T:System.ServiceModel.Description.IContractBehaviorAttribute">
          <source>The following code example assumes a custom <ph id="ph1">&lt;xref:System.ServiceModel.Dispatcher.IInstanceProvider?displayProperty=nameWithType&gt;</ph> implementation called <ph id="ph2">`ObjectProviderBehavior`</ph> that provides a "singleton" behavior; it always returns the same service instance and does not recycle it.</source>
          <target state="translated">下面的代码示例假定自定义 <ph id="ph1">&lt;xref:System.ServiceModel.Dispatcher.IInstanceProvider?displayProperty=nameWithType&gt;</ph> 实现调用了可提供“单一实例”行为的 <ph id="ph2">`ObjectProviderBehavior`</ph>，它始终返回同一服务实例，且不回收该服务实例。</target>       </trans-unit>
        <trans-unit id="106" translate="yes" xml:space="preserve" extradata="MT" uid="T:System.ServiceModel.Description.IContractBehaviorAttribute">
          <source>To insert the instance provider customization, the example shows how to implement a custom attribute (<ph id="ph1">`SingletonBehaviorAttribute`</ph>) that implements <ph id="ph2">&lt;xref:System.ServiceModel.Description.IContractBehavior?displayProperty=nameWithType&gt;</ph> to insert the custom service instance provider.</source>
          <target state="translated">对于实例提供程序自定义的插入，该示例演示了如何实现一个自定义属性 (<ph id="ph1">`SingletonBehaviorAttribute`</ph>)，该自定义属性可实现 <ph id="ph2">&lt;xref:System.ServiceModel.Description.IContractBehavior?displayProperty=nameWithType&gt;</ph>，从而插入自定义服务实例提供程序。</target>       </trans-unit>
        <trans-unit id="107" translate="yes" xml:space="preserve" extradata="MT" uid="T:System.ServiceModel.Description.IContractBehaviorAttribute">
          <source>It also implements <ph id="ph1">&lt;xref:System.ServiceModel.Description.IContractBehaviorAttribute&gt;</ph>, which binds its application to the <ph id="ph2">`ISampleService`</ph> contract.</source>
          <target state="translated">它还实现了 <ph id="ph1">&lt;xref:System.ServiceModel.Description.IContractBehaviorAttribute&gt;</ph>，这会将其应用程序绑定到 <ph id="ph2">`ISampleService`</ph> 协定。</target>       </trans-unit>
        <trans-unit id="108" translate="yes" xml:space="preserve" uid="P:System.ServiceModel.Description.IContractBehaviorAttribute.TargetContract">
          <source>Gets the type of the contract to which the contract behavior is applicable.</source>
          <target state="translated">获取可用该协定行为的协定的类型。</target>       </trans-unit>
        <trans-unit id="109" translate="yes" xml:space="preserve" extradata="MT" uid="P:System.ServiceModel.Description.IContractBehaviorAttribute.TargetContract">
          <source>The contract to which the contract behavior is applicable.</source>
          <target state="translated">适用于该协定行为的协定。</target>       </trans-unit>
        <trans-unit id="110" translate="yes" xml:space="preserve" extradata="MT" uid="P:System.ServiceModel.Description.IContractBehaviorAttribute.TargetContract">
          <source>Implement the <ph id="ph1">&lt;xref:System.ServiceModel.Description.IContractBehaviorAttribute.TargetContract%2A&gt;</ph> property to specify the contract to which the contract behavior is applied when the implementing <ph id="ph2">&lt;xref:System.ServiceModel.Description.IContractBehavior?displayProperty=nameWithType&gt;</ph> attribute is applied to a service class.</source>
          <target state="translated">实现 <ph id="ph1">&lt;xref:System.ServiceModel.Description.IContractBehaviorAttribute.TargetContract%2A&gt;</ph> 属性可以在将实现 <ph id="ph2">&lt;xref:System.ServiceModel.Description.IContractBehavior?displayProperty=nameWithType&gt;</ph> 属性应用到服务类时，指定该协定行为要应用到的协定。</target>       </trans-unit>
        <trans-unit id="111" translate="yes" xml:space="preserve" extradata="MT" uid="P:System.ServiceModel.Description.IContractBehaviorAttribute.TargetContract">
          <source>The following code example assumes a custom <ph id="ph1">&lt;xref:System.ServiceModel.Dispatcher.IInstanceProvider?displayProperty=nameWithType&gt;</ph> implementation called <ph id="ph2">`ObjectProviderBehavior`</ph> that provides a "singleton" behavior; it always returns the same service instance and does not recycle it.</source>
          <target state="translated">下面的代码示例假定自定义 <ph id="ph1">&lt;xref:System.ServiceModel.Dispatcher.IInstanceProvider?displayProperty=nameWithType&gt;</ph> 实现调用了可提供“单一实例”行为的 <ph id="ph2">`ObjectProviderBehavior`</ph>，它始终返回同一服务实例，且不回收该服务实例。</target>       </trans-unit>
        <trans-unit id="112" translate="yes" xml:space="preserve" extradata="MT" uid="P:System.ServiceModel.Description.IContractBehaviorAttribute.TargetContract">
          <source>To insert the instance provider customization, the example shows how to implement a custom attribute (<ph id="ph1">`SingletonBehaviorAttribute`</ph>) that implements <ph id="ph2">&lt;xref:System.ServiceModel.Description.IContractBehavior?displayProperty=nameWithType&gt;</ph> to insert the custom service instance provider.</source>
          <target state="translated">对于实例提供程序自定义的插入，该示例演示了如何实现一个自定义属性 (<ph id="ph1">`SingletonBehaviorAttribute`</ph>)，该自定义属性可实现 <ph id="ph2">&lt;xref:System.ServiceModel.Description.IContractBehavior?displayProperty=nameWithType&gt;</ph>，从而插入自定义服务实例提供程序。</target>       </trans-unit>
        <trans-unit id="113" translate="yes" xml:space="preserve" extradata="MT" uid="P:System.ServiceModel.Description.IContractBehaviorAttribute.TargetContract">
          <source>It also implements <ph id="ph1">&lt;xref:System.ServiceModel.Description.IContractBehaviorAttribute&gt;</ph>, which binds its application to the <ph id="ph2">`ISampleService`</ph> contract.</source>
          <target state="translated">它还实现了 <ph id="ph1">&lt;xref:System.ServiceModel.Description.IContractBehaviorAttribute&gt;</ph>，这会将其应用程序绑定到 <ph id="ph2">`ISampleService`</ph> 协定。</target>       </trans-unit>
      </group>
    </body>
  </file>
</xliff>