<?xml version="1.0" encoding="utf-8"?>
<xliff xmlns="urn:oasis:names:tc:xliff:document:1.2" xmlns:xsi="http://www.w3.org/2001/XMLSchema-instance" version="1.2" xsi:schemaLocation="urn:oasis:names:tc:xliff:document:1.2 xliff-core-1.2-transitional.xsd">
  <file datatype="xml" original="WebHttpSecurity.xml" source-language="en-US" target-language="zh-CN">
    <header>
      <tool tool-id="mdxliff" tool-name="mdxliff" tool-version="1.0-15c36f0" tool-company="Microsoft" />
      <xliffext:skl_file_name xmlns:xliffext="urn:microsoft:content:schema:xliffextensions">02cd5861-7ce2-4a82-b358-31f8435a0ac5b550ffa6b30c5562787c92200bf9310d37ac5d5a.skl</xliffext:skl_file_name>
      <xliffext:version xmlns:xliffext="urn:microsoft:content:schema:xliffextensions">1.2</xliffext:version>
      <xliffext:ms.openlocfilehash xmlns:xliffext="urn:microsoft:content:schema:xliffextensions">b550ffa6b30c5562787c92200bf9310d37ac5d5a</xliffext:ms.openlocfilehash>
      <xliffext:ms.sourcegitcommit xmlns:xliffext="urn:microsoft:content:schema:xliffextensions">d31dc2ede16f6f7bc64e90d9f897ff54c4e3869b</xliffext:ms.sourcegitcommit>
      <xliffext:ms.lasthandoff xmlns:xliffext="urn:microsoft:content:schema:xliffextensions">04/03/2018</xliffext:ms.lasthandoff>
      <xliffext:moniker_ids xmlns:xliffext="urn:microsoft:content:schema:xliffextensions">netframework-4.5.1,netframework-4.5.2,netframework-4.5,netframework-4.6.1,netframework-4.6.2,netframework-4.6,netframework-4.7.1,netframework-4.7,xamarinandroid-7.1,xamarinios-10.8,xamarinmac-3.0</xliffext:moniker_ids>
    </header>
    <body>
      <group id="content" extype="content">
        <trans-unit id="101" translate="yes" xml:space="preserve" uid="T:System.ServiceModel.WebHttpSecurity">
          <source>Specifies the types of security available to a service endpoint configured to receive HTTP requests.</source>
          <target state="translated">指定可用于配置为接收 HTTP 请求的服务终结点的安全类型。</target>       </trans-unit>
        <trans-unit id="102" translate="yes" xml:space="preserve" extradata="MT" uid="T:System.ServiceModel.WebHttpSecurity">
          <source><ph id="ph1">&lt;xref:System.ServiceModel.WebHttpSecurity&gt;</ph> provides the security requirements for an endpoint configured with a <ph id="ph2">&lt;xref:System.ServiceModel.WebHttpBinding&gt;</ph>.</source>
          <target state="translated"><ph id="ph1">&lt;xref:System.ServiceModel.WebHttpSecurity&gt;</ph> 为用 T:System.ServiceModel.WebHttpBinding<ph id="ph2">&lt;xref:System.ServiceModel.WebHttpBinding&gt;</ph> 配置的终结点提供安全要求。</target>       </trans-unit>
        <trans-unit id="103" translate="yes" xml:space="preserve" extradata="MT" uid="T:System.ServiceModel.WebHttpSecurity">
          <source>If the <ph id="ph1">&lt;xref:System.ServiceModel.WebHttpSecurityMode.Transport&gt;</ph> value is specified by the <ph id="ph2">&lt;xref:System.ServiceModel.WebHttpBinding.%23ctor%28System.ServiceModel.WebHttpSecurityMode%29&gt;</ph> method, then the settings provided by the <ph id="ph3">&lt;xref:System.ServiceModel.WebHttpSecurity.Transport%2A&gt;</ph> property become effective for the service endpoint.</source>
          <target state="translated">如果 <ph id="ph1">&lt;xref:System.ServiceModel.WebHttpSecurityMode.Transport&gt;</ph> 方法指定了 <ph id="ph2">&lt;xref:System.ServiceModel.WebHttpBinding.%23ctor%28System.ServiceModel.WebHttpSecurityMode%29&gt;</ph> 值，则 <ph id="ph3">&lt;xref:System.ServiceModel.WebHttpSecurity.Transport%2A&gt;</ph> 属性提供的设置就会对服务终结点有效。</target>       </trans-unit>
        <trans-unit id="104" translate="yes" xml:space="preserve" extradata="MT" uid="T:System.ServiceModel.WebHttpSecurity">
          <source>The value of <ph id="ph1">&lt;xref:System.ServiceModel.WebHttpSecurityMode&gt;</ph> can only be set in the <ph id="ph2">&lt;xref:System.ServiceModel.WebHttpBinding&gt;</ph> constructor that takes it as an explicit parameter and its value cannot be set again after the binding instance is created.</source>
          <target state="translated"><ph id="ph1">&lt;xref:System.ServiceModel.WebHttpSecurityMode&gt;</ph> 的值只能在将其作为显式参数的 <ph id="ph2">&lt;xref:System.ServiceModel.WebHttpBinding&gt;</ph> 构造函数中设置，并且在创建绑定实例之后无法再次设置其值。</target>       </trans-unit>
        <trans-unit id="105" translate="yes" xml:space="preserve" uid="M:System.ServiceModel.WebHttpSecurity.#ctor">
          <source>Creates a new instance of the <ph id="ph1">&lt;see cref="T:System.ServiceModel.WebHttpSecurity" /&gt;</ph> class.</source>
          <target state="translated">创建 <ph id="ph1">&lt;see cref="T:System.ServiceModel.WebHttpSecurity" /&gt;</ph> 类的新实例。</target>       </trans-unit>
        <trans-unit id="106" translate="yes" xml:space="preserve" uid="P:System.ServiceModel.WebHttpSecurity.Mode">
          <source>Gets or sets the mode of security that is used by an endpoint configured to receive HTTP requests with a <ph id="ph1">&lt;see cref="T:System.ServiceModel.WebHttpBinding" /&gt;</ph>.</source>
          <target state="translated">获取或设置使用 <ph id="ph1">&lt;see cref="T:System.ServiceModel.WebHttpBinding" /&gt;</ph> 配置为接收 HTTP 请求的终结点所使用的安全模式。</target>       </trans-unit>
        <trans-unit id="107" translate="yes" xml:space="preserve" extradata="MT" uid="P:System.ServiceModel.WebHttpSecurity.Mode">
          <source>A value of the <ph id="ph1">&lt;see cref="T:System.ServiceModel.WebHttpSecurityMode" /&gt;</ph> that indicates whether transport-level security or no security is used by an endpoint.</source>
          <target state="translated">一个 <ph id="ph1">&lt;see cref="T:System.ServiceModel.WebHttpSecurityMode" /&gt;</ph> 的值，它指示终结点是使用传输级安全，还是使用非安全。</target>       </trans-unit>
        <trans-unit id="108" translate="yes" xml:space="preserve" extradata="MT" uid="P:System.ServiceModel.WebHttpSecurity.Mode">
          <source>The default value is <ph id="ph1">&lt;see cref="F:System.ServiceModel.WebHttpSecurityMode.None" /&gt;</ph>.</source>
          <target state="translated">默认值为 <ph id="ph1">&lt;see cref="F:System.ServiceModel.WebHttpSecurityMode.None" /&gt;</ph>。</target>       </trans-unit>
        <trans-unit id="109" translate="yes" xml:space="preserve" extradata="MT" uid="P:System.ServiceModel.WebHttpSecurity.Mode">
          <source>This property determines whether the settings from the <ph id="ph1">&lt;xref:System.ServiceModel.WebHttpSecurity.Transport%2A&gt;</ph> property becomes effective.</source>
          <target state="translated">此属性确定 <ph id="ph1">&lt;xref:System.ServiceModel.WebHttpSecurity.Transport%2A&gt;</ph> 属性的设置是否会成为有效设置。</target>       </trans-unit>
        <trans-unit id="110" translate="yes" xml:space="preserve" uid="P:System.ServiceModel.WebHttpSecurity.Mode">
          <source>The value is not a valid <ph id="ph1">&lt;see cref="T:System.ServiceModel.WebHttpSecurityMode" /&gt;</ph>.</source>
          <target state="translated">该值不是有效的 <ph id="ph1">&lt;see cref="T:System.ServiceModel.WebHttpSecurityMode" /&gt;</ph>。</target>       </trans-unit>
        <trans-unit id="111" translate="yes" xml:space="preserve" uid="M:System.ServiceModel.WebHttpSecurity.ShouldSerializeMode">
          <source>Specifies whether the <ph id="ph1">&lt;see cref="P:System.ServiceModel.WebHttpSecurity.Mode" /&gt;</ph> property has changed from its default and should be serialized.</source>
          <target state="translated">指定 <ph id="ph1">&lt;see cref="P:System.ServiceModel.WebHttpSecurity.Mode" /&gt;</ph> 属性是否已更改，不再是默认值并应对其进行序列化。</target>       </trans-unit>
        <trans-unit id="112" translate="yes" xml:space="preserve" uid="M:System.ServiceModel.WebHttpSecurity.ShouldSerializeMode">
          <source>This is used for XAML integration.</source>
          <target state="translated">它用于进行 XAML 集成。</target>       </trans-unit>
        <trans-unit id="113" translate="yes" xml:space="preserve" uid="M:System.ServiceModel.WebHttpSecurity.ShouldSerializeMode">
          <source><ph id="ph1">&lt;see langword="true" /&gt;</ph> if the <ph id="ph2">&lt;see cref="P:System.ServiceModel.WebHttpSecurity.Mode" /&gt;</ph> property value should be serialized; otherwise, <ph id="ph3">&lt;see langword="false" /&gt;</ph>.</source>
          <target state="translated">如果应当序列化 <ph id="ph2">&lt;see cref="P:System.ServiceModel.WebHttpSecurity.Mode" /&gt;</ph> 属性值，则为 <ph id="ph1">&lt;see langword="true" /&gt;</ph>；否则为 <ph id="ph3">&lt;see langword="false" /&gt;</ph>。</target>       </trans-unit>
        <trans-unit id="114" translate="yes" xml:space="preserve" uid="M:System.ServiceModel.WebHttpSecurity.ShouldSerializeTransport">
          <source>Returns a value that indicates whether the Transport property has changed from its default value and should be serialized.</source>
          <target state="translated">返回一个值，该值指示 Transport 属性是否已更改，不再是默认值且应对其进行序列化。</target>       </trans-unit>
        <trans-unit id="115" translate="yes" xml:space="preserve" uid="M:System.ServiceModel.WebHttpSecurity.ShouldSerializeTransport">
          <source>This is used by WCF for XAML integration.</source>
          <target state="translated">WCF 使用此项进行 XAML 集成。</target>       </trans-unit>
        <trans-unit id="116" translate="yes" xml:space="preserve" uid="M:System.ServiceModel.WebHttpSecurity.ShouldSerializeTransport">
          <source><ph id="ph1">&lt;see langword="true" /&gt;</ph> if the <ph id="ph2">&lt;see cref="P:System.ServiceModel.WebHttpSecurity.Transport" /&gt;</ph> property value should be serialized; otherwise, <ph id="ph3">&lt;see langword="false" /&gt;</ph>.</source>
          <target state="translated">如果应当序列化 <ph id="ph2">&lt;see cref="P:System.ServiceModel.WebHttpSecurity.Transport" /&gt;</ph> 属性值，则为 <ph id="ph1">&lt;see langword="true" /&gt;</ph>；否则为 <ph id="ph3">&lt;see langword="false" /&gt;</ph>。</target>       </trans-unit>
        <trans-unit id="117" translate="yes" xml:space="preserve" uid="P:System.ServiceModel.WebHttpSecurity.Transport">
          <source>Gets an object that contains the transport-level security settings for this binding.</source>
          <target state="translated">获取一个包含此绑定的传输级安全性设置的对象。</target>       </trans-unit>
        <trans-unit id="118" translate="yes" xml:space="preserve" extradata="MT" uid="P:System.ServiceModel.WebHttpSecurity.Transport">
          <source>The <ph id="ph1">&lt;see cref="T:System.ServiceModel.HttpTransportSecurity" /&gt;</ph> for this binding.</source>
          <target state="translated">此绑定的 <ph id="ph1">&lt;see cref="T:System.ServiceModel.HttpTransportSecurity" /&gt;</ph>。</target>       </trans-unit>
        <trans-unit id="119" translate="yes" xml:space="preserve" extradata="MT" uid="P:System.ServiceModel.WebHttpSecurity.Transport">
          <source>The default values set are a <ph id="ph1">&lt;see cref="P:System.ServiceModel.HttpTransportSecurity.ClientCredentialType" /&gt;</ph> of <ph id="ph2">&lt;see cref="F:System.ServiceModel.HttpClientCredentialType.None" /&gt;</ph>, a <ph id="ph3">&lt;see cref="P:System.ServiceModel.HttpTransportSecurity.ProxyCredentialType" /&gt;</ph> of <ph id="ph4">&lt;see cref="F:System.ServiceModel.HttpProxyCredentialType.None" /&gt;</ph>, and <ph id="ph5">&lt;see cref="P:System.ServiceModel.HttpTransportSecurity.Realm" /&gt;</ph> = "".</source>
          <target state="translated">默认值设置为 <ph id="ph1">&lt;see cref="P:System.ServiceModel.HttpTransportSecurity.ClientCredentialType" /&gt;</ph> 的 <ph id="ph2">&lt;see cref="F:System.ServiceModel.HttpClientCredentialType.None" /&gt;</ph>，<ph id="ph3">&lt;see cref="P:System.ServiceModel.HttpTransportSecurity.ProxyCredentialType" /&gt;</ph> 的 <ph id="ph4">&lt;see cref="F:System.ServiceModel.HttpProxyCredentialType.None" /&gt;</ph> 和 <ph id="ph5">&lt;see cref="P:System.ServiceModel.HttpTransportSecurity.Realm" /&gt;</ph> = ""。</target>       </trans-unit>
        <trans-unit id="120" translate="yes" xml:space="preserve" extradata="MT" uid="P:System.ServiceModel.WebHttpSecurity.Transport">
          <source>Use the <ph id="ph1">&lt;xref:System.ServiceModel.HttpTransportSecurity&gt;</ph> object returned by this property to set the transport security parameters for the <ph id="ph2">&lt;xref:System.ServiceModel.WebHttpBinding&gt;</ph>.</source>
          <target state="translated">使用此属性返回的 <ph id="ph1">&lt;xref:System.ServiceModel.HttpTransportSecurity&gt;</ph> 对象设置 <ph id="ph2">&lt;xref:System.ServiceModel.WebHttpBinding&gt;</ph> 的传输安全参数。</target>       </trans-unit>
        <trans-unit id="121" translate="yes" xml:space="preserve" extradata="MT" uid="P:System.ServiceModel.WebHttpSecurity.Transport">
          <source>If the <ph id="ph1">&lt;xref:System.ServiceModel.WebHttpSecurityMode.Transport&gt;</ph> or <ph id="ph2">&lt;xref:System.ServiceModel.WebHttpSecurityMode.TransportCredentialOnly&gt;</ph> value is specified by the <ph id="ph3">&lt;xref:System.ServiceModel.WebHttpBinding.%23ctor%28System.ServiceModel.WebHttpSecurityMode%29&gt;</ph> method, then the settings provided by the <ph id="ph4">&lt;xref:System.ServiceModel.WebHttpSecurity.Transport%2A&gt;</ph> property become effective for the service endpoint.</source>
          <target state="translated">如果 <ph id="ph1">&lt;xref:System.ServiceModel.WebHttpSecurityMode.Transport&gt;</ph> 方法指定了 <ph id="ph2">&lt;xref:System.ServiceModel.WebHttpSecurityMode.TransportCredentialOnly&gt;</ph> 或 <ph id="ph3">&lt;xref:System.ServiceModel.WebHttpBinding.%23ctor%28System.ServiceModel.WebHttpSecurityMode%29&gt;</ph> 值，则 <ph id="ph4">&lt;xref:System.ServiceModel.WebHttpSecurity.Transport%2A&gt;</ph> 属性提供的设置就会对服务终结点有效。</target>       </trans-unit>
        <trans-unit id="122" translate="yes" xml:space="preserve" extradata="MT" uid="P:System.ServiceModel.WebHttpSecurity.Transport">
          <source>If the <ph id="ph1">&lt;xref:System.ServiceModel.WebHttpSecurityMode.TransportCredentialOnly&gt;</ph> value is specified by the <ph id="ph2">&lt;xref:System.ServiceModel.WebHttpBinding.%23ctor%28System.ServiceModel.WebHttpSecurityMode%29&gt;</ph> method, then the settings provided by the <ph id="ph3">&lt;xref:System.ServiceModel.WebHttpSecurity.Transport%2A&gt;</ph> property become effective for the service endpoint.</source>
          <target state="translated">如果 <ph id="ph1">&lt;xref:System.ServiceModel.WebHttpSecurityMode.TransportCredentialOnly&gt;</ph> 方法指定了 <ph id="ph2">&lt;xref:System.ServiceModel.WebHttpBinding.%23ctor%28System.ServiceModel.WebHttpSecurityMode%29&gt;</ph> 值，则 <ph id="ph3">&lt;xref:System.ServiceModel.WebHttpSecurity.Transport%2A&gt;</ph> 属性提供的设置就会对服务终结点有效。</target>       </trans-unit>
        <trans-unit id="123" translate="yes" xml:space="preserve" extradata="MT" uid="P:System.ServiceModel.WebHttpSecurity.Transport">
          <source>The value of <ph id="ph1">&lt;xref:System.ServiceModel.WebHttpSecurityMode&gt;</ph> can only be set in the <ph id="ph2">&lt;xref:System.ServiceModel.WebHttpBinding&gt;</ph> constructor that takes it as an explicit parameter and its value cannot be set again after the binding instance is created.</source>
          <target state="translated"><ph id="ph1">&lt;xref:System.ServiceModel.WebHttpSecurityMode&gt;</ph> 的值只能在将其作为显式参数的 <ph id="ph2">&lt;xref:System.ServiceModel.WebHttpBinding&gt;</ph> 构造函数中设置，并且在创建绑定实例之后无法再次设置其值。</target>       </trans-unit>
      </group>
    </body>
  </file>
</xliff>